franka_rust-0.1.7.dist-info/METADATA
franka_rust-0.1.7.dist-info/WHEEL
franka_rust/__init__.py
franka_rust/__init__.pyi
franka_rust/franka_rust.cp38-win32.pyd
franka_rust/py.typed
franka_rust-0.1.7.dist-info/RECORD
