Metadata-Version: 2.4
Name: franka_rust
Version: 0.1.7
Summary: Rust bindings for the Franka Emika Panda robot
Keywords: franka,emika,panda,libfranka
Author: Yixing <yanjizhou312@163.com>
Author-email: Yixing <yanjizhou312@163.com>
License: Apache-2.0
Project-URL: Source Code, https://github.com/Robot-Exp-Platform/franka-rust
